Workbook

Sheet Start Here
B2: Booth Profit Tracker
B3: Know if your booth is actually making money.
B5: HOW TO USE IT (about 10 minutes to set up)
B6: 1. Go to the Booth Setup tab. Fill in the YELLOW cells: rent, store commission, card fee, booth size.
B7: 2. Go to the Inventory & Sales tab. Add each item when it goes in your booth (cost, tag price, date in).
B8: 3. When something sells, fill in the Date Sold and Sale Price. Profit figures itself out.
B9: 4. Check the Monthly Summary tab. It shows profit or loss for every month, after rent and fees.
B11: COLOR KEY
B12: Yellow cells = you type here. White cells = the sheet does the math. Don't type over them.
B13: Items that sit unsold longer than your 'stale' limit turn red, so you know what to mark down or pull.
B15: TIPS
B16: Rent a booth in more than one store? Make a copy of this file for each booth.
... B18: The example row on the Inventory & Sales tab is there to show you the format. Delete it when you start.

Sheet Booth Setup
B2: Booth Setup
B3: Fill in the yellow cells. Everything else updates on its own.
B5: YOUR NUMBERS
B6: Store / mall name | C6: Example Antique Mall | D6: Just a label for you.
B7: Monthly booth rent | C7: 150 | D7: What you pay the store each month.
B8: Store commission on sales | C8: 0.1 | D8: The store's cut of each sale. 10% = type 10%.
B9: Card processing fee | C9: 0.03 | D9: If the store passes card fees to you. Put 0% if not.
B10: Booth size (square feet) | C10: 100 | D10: Example: a 10 x 10 booth = 100 sq ft.
B11: Other monthly costs (supplies, gas, etc.) | C11: 25 | D11: Tags, bags, cleaning supplies, trips to restock.
B12: Days before an item counts as 'stale' | C12: 90 | D12: Unsold items older than this turn red on the log.
B15: WHAT IT MEANS
B16: Fixed costs each month | C16: =C7+C11 -> 175 | D16: Rent plus other costs. You pay these even if nothing sells.
B17: You keep this much of every $1 sold | C17: =1-C8-C9 -> 0.87 | D17: After the store's cut and card fees.
B18: Rent cost per square foot, per month | C18: =IFERROR(C7/C10,0) -> 1.5 | D18: Every square foot of your booth has to earn at least this much.
B19: BREAK-EVEN: sales needed each month* | C19: =IFERROR(C16/C17,0) -> 201.14943 | D19: *Before item costs. Sell less than this and the booth loses money.
B20: Break-even, per week | C20: =C19*12/52 -> 46.419098 | D20: Same target, broken into weeks.
B22: Break-even with items: the Monthly Summary tab adds what you paid for the items you sold, so it shows true profit.

Sheet Inventory & Sales
A1: Item | B1: Category | C1: Date In | D1: What You Paid | E1: Tag Price | F1: Date Sold | G1: Sale Price | H1: Store Commission | I1: Card Fee | J1: Profit on Item | K1: Days in Booth | L1: Status | M1: Month Sold
A2: Example: Pyrex mixing bowl (delete me) | B2: Kitchen | C2: 46237 | D2: 4 | E2: 18 | F2: 46255 | G2: 16 | H2: =IF(G2="","",G2*'Booth Setup'!$C$8) -> 1.6 | I2: =IF(G2="","",G2*'Booth Setup'!$C$9) -> 0.48 | J2: =IF(G2="","",G2-H2-I2-D2) -> 9.92 | K2: =IF(C2="","",IF(F2="",TODAY(),F2)-C2) -> 18 | L2: =IF(A2="","",IF(G2<>"","Sold",IF(K2>'Booth Setup'!$C$12,"STALE - mark down","In booth"))) -> Sold | M2: =IF(F2="","",DATE(YEAR(F2),MONTH(F2),1)) -> 46235
H3: =IF(G3="","",G3*'Booth Setup'!$C$8) | I3: =IF(G3="","",G3*'Booth Setup'!$C$9) | J3: =IF(G3="","",G3-H3-I3-D3) | K3: =IF(C3="","",IF(F3="",TODAY(),F3)-C3) | L3: =IF(A3="","",IF(G3<>"","Sold",IF(K3>'Booth Setup'!$C$12,"STALE - mark down","In booth"))) | M3: =IF(F3="","",DATE(YEAR(F3),MONTH(F3),1))
H4: =IF(G4="","",G4*'Booth Setup'!$C$8) | I4: =IF(G4="","",G4*'Booth Setup'!$C$9) | J4: =IF(G4="","",G4-H4-I4-D4) | K4: =IF(C4="","",IF(F4="",TODAY(),F4)-C4) | L4: =IF(A4="","",IF(G4<>"","Sold",IF(K4>'Booth Setup'!$C$12,"STALE - mark down","In booth"))) | M4: =IF(F4="","",DATE(YEAR(F4),MONTH(F4),1))
H5: =IF(G5="","",G5*'Booth Setup'!$C$8) | I5: =IF(G5="","",G5*'Booth Setup'!$C$9) | J5: =IF(G5="","",G5-H5-I5-D5) | K5: =IF(C5="","",IF(F5="",TODAY(),F5)-C5) | L5: =IF(A5="","",IF(G5<>"","Sold",IF(K5>'Booth Setup'!$C$12,"STALE - mark down","In booth"))) | M5: =IF(F5="","",DATE(YEAR(F5),MONTH(F5),1))
H6: =IF(G6="","",G6*'Booth Setup'!$C$8) | I6: =IF(G6="","",G6*'Booth Setup'!$C$9) | J6: =IF(G6="","",G6-H6-I6-D6) | K6: =IF(C6="","",IF(F6="",TODAY(),F6)-C6) | L6: =IF(A6="","",IF(G6<>"","Sold",IF(K6>'Booth Setup'!$C$12,"STALE - mark down","In booth"))) | M6: =IF(F6="","",DATE(YEAR(F6),MONTH(F6),1))
H7: =IF(G7="","",G7*'Booth Setup'!$C$8) | I7: =IF(G7="","",G7*'Booth Setup'!$C$9) | J7: =IF(G7="","",G7-H7-I7-D7) | K7: =IF(C7="","",IF(F7="",TODAY(),F7)-C7) | L7: =IF(A7="","",IF(G7<>"","Sold",IF(K7>'Booth Setup'!$C$12,"STALE - mark down","In booth"))) | M7: =IF(F7="","",DATE(YEAR(F7),MONTH(F7),1))
H8: =IF(G8="","",G8*'Booth Setup'!$C$8) | I8: =IF(G8="","",G8*'Booth Setup'!$C$9) | J8: =IF(G8="","",G8-H8-I8-D8) | K8: =IF(C8="","",IF(F8="",TODAY(),F8)-C8) | L8: =IF(A8="","",IF(G8<>"","Sold",IF(K8>'Booth Setup'!$C$12,"STALE - mark down","In booth"))) | M8: =IF(F8="","",DATE(YEAR(F8),MONTH(F8),1))
H9: =IF(G9="","",G9*'Booth Setup'!$C$8) | I9: =IF(G9="","",G9*'Booth Setup'!$C$9) | J9: =IF(G9="","",G9-H9-I9-D9) | K9: =IF(C9="","",IF(F9="",TODAY(),F9)-C9) | L9: =IF(A9="","",IF(G9<>"","Sold",IF(K9>'Booth Setup'!$C$12,"STALE - mark down","In booth"))) | M9: =IF(F9="","",DATE(YEAR(F9),MONTH(F9),1))
H10: =IF(G10="","",G10*'Booth Setup'!$C$8) | I10: =IF(G10="","",G10*'Booth Setup'!$C$9) | J10: =IF(G10="","",G10-H10-I10-D10) | K10: =IF(C10="","",IF(F10="",TODAY(),F10)-C10) | L10: =IF(A10="","",IF(G10<>"","Sold",IF(K10>'Booth Setup'!$C$12,"STALE - mark down","In booth"))) | M10: =IF(F10="","",DATE(YEAR(F10),MONTH(F10),1))
H11: =IF(G11="","",G11*'Booth Setup'!$C$8) | I11: =IF(G11="","",G11*'Booth Setup'!$C$9) | J11: =IF(G11="","",G11-H11-I11-D11) | K11: =IF(C11="","",IF(F11="",TODAY(),F11)-C11) | L11: =IF(A11="","",IF(G11<>"","Sold",IF(K11>'Booth Setup'!$C$12,"STALE - mark down","In booth"))) | M11: =IF(F11="","",DATE(YEAR(F11),MONTH(F11),1))
H12: =IF(G12="","",G12*'Booth Setup'!$C$8) | I12: =IF(G12="","",G12*'Booth Setup'!$C$9) | J12: =IF(G12="","",G12-H12-I12-D12) | K12: =IF(C12="","",IF(F12="",TODAY(),F12)-C12) | L12: =IF(A12="","",IF(G12<>"","Sold",IF(K12>'Booth Setup'!$C$12,"STALE - mark down","In booth"))) | M12: =IF(F12="","",DATE(YEAR(F12),MONTH(F12),1))
H13: =IF(G13="","",G13*'Booth Setup'!$C$8) | I13: =IF(G13="","",G13*'Booth Setup'!$C$9) | J13: =IF(G13="","",G13-H13-I13-D13) | K13: =IF(C13="","",IF(F13="",TODAY(),F13)-C13) | L13: =IF(A13="","",IF(G13<>"","Sold",IF(K13>'Booth Setup'!$C$12,"STALE - mark down","In booth"))) | M13: =IF(F13="","",DATE(YEAR(F13),MONTH(F13),1))
H14: =IF(G14="","",G14*'Booth Setup'!$C$8) | I14: =IF(G14="","",G14*'Booth Setup'!$C$9) | J14: =IF(G14="","",G14-H14-I14-D14) | K14: =IF(C14="","",IF(F14="",TODAY(),F14)-C14) | L14: =IF(A14="","",IF(G14<>"","Sold",IF(K14>'Booth Setup'!$C$12,"STALE - mark down","In booth"))) | M14: =IF(F14="","",DATE(YEAR(F14),MONTH(F14),1))
... H251: =IF(G251="","",G251*'Booth Setup'!$C$8) | I251: =IF(G251="","",G251*'Booth Setup'!$C$9) | J251: =IF(G251="","",G251-H251-I251-D251) | K251: =IF(C251="","",IF(F251="",TODAY(),F251)-C251) | L251: =IF(A251="","",IF(G251<>"","Sold",IF(K251>'Booth Setup'!$C$12,"STALE - mark down","In booth"))) | M251: =IF(F251="","",DATE(YEAR(F251),MONTH(F251),1))

Sheet Monthly Summary
B2: Monthly Summary
B3: Type the first month you want to track in the yellow cell. The rest fills in.
B4: Start month: | C4: 46235
B6: Month | C6: Items Sold | D6: Sales | E6: What You Paid for Items | F6: Store Commission | G6: Card Fees | H6: Booth Rent | I6: Other Costs | J6: NET PROFIT | K6: Result
B7: =C4 -> 46235 | C7: =COUNTIFS('Inventory & Sales'!$M$2:$M$251,B7) -> 1 | D7: =SUMIFS('Inventory & Sales'!$G$2:$G$251,'Inventory & Sales'!$M$2:$M$251,B7) -> 16 | E7: =SUMIFS('Inventory & Sales'!$D$2:$D$251,'Inventory & Sales'!$M$2:$M$251,B7) -> 4 | F7: =SUMIFS('Inventory & Sales'!$H$2:$H$251,'Inventory & Sales'!$M$2:$M$251,B7) -> 1.6 | G7: =SUMIFS('Inventory & Sales'!$I$2:$I$251,'Inventory & Sales'!$M$2:$M$251,B7) -> 0.48 | H7: ='Booth Setup'!$C$7 -> 150 | I7: ='Booth Setup'!$C$11 -> 25 | J7: =D7-E7-F7-G7-H7-I7 -> -165.08 | K7: =IF(C7=0,"No sales logged",IF(J7>=0,"Made money","Lost money")) -> Lost money
B8: =DATE(YEAR(B7),MONTH(B7)+1,1) -> 46266 | C8: =COUNTIFS('Inventory & Sales'!$M$2:$M$251,B8) -> 0 | D8: =SUMIFS('Inventory & Sales'!$G$2:$G$251,'Inventory & Sales'!$M$2:$M$251,B8) -> 0 | E8: =SUMIFS('Inventory & Sales'!$D$2:$D$251,'Inventory & Sales'!$M$2:$M$251,B8) -> 0 | F8: =SUMIFS('Inventory & Sales'!$H$2:$H$251,'Inventory & Sales'!$M$2:$M$251,B8) -> 0 | G8: =SUMIFS('Inventory & Sales'!$I$2:$I$251,'Inventory & Sales'!$M$2:$M$251,B8) -> 0 | H8: ='Booth Setup'!$C$7 -> 150 | I8: ='Booth Setup'!$C$11 -> 25 | J8: =D8-E8-F8-G8-H8-I8 -> -175 | K8: =IF(C8=0,"No sales logged",IF(J8>=0,"Made money","Lost money")) -> No sales logged
B9: =DATE(YEAR(B8),MONTH(B8)+1,1) -> 46296 | C9: =COUNTIFS('Inventory & Sales'!$M$2:$M$251,B9) -> 0 | D9: =SUMIFS('Inventory & Sales'!$G$2:$G$251,'Inventory & Sales'!$M$2:$M$251,B9) -> 0 | E9: =SUMIFS('Inventory & Sales'!$D$2:$D$251,'Inventory & Sales'!$M$2:$M$251,B9) -> 0 | F9: =SUMIFS('Inventory & Sales'!$H$2:$H$251,'Inventory & Sales'!$M$2:$M$251,B9) -> 0 | G9: =SUMIFS('Inventory & Sales'!$I$2:$I$251,'Inventory & Sales'!$M$2:$M$251,B9) -> 0 | H9: ='Booth Setup'!$C$7 -> 150 | I9: ='Booth Setup'!$C$11 -> 25 | J9: =D9-E9-F9-G9-H9-I9 -> -175 | K9: =IF(C9=0,"No sales logged",IF(J9>=0,"Made money","Lost money")) -> No sales logged
B10: =DATE(YEAR(B9),MONTH(B9)+1,1) -> 46327 | C10: =COUNTIFS('Inventory & Sales'!$M$2:$M$251,B10) -> 0 | D10: =SUMIFS('Inventory & Sales'!$G$2:$G$251,'Inventory & Sales'!$M$2:$M$251,B10) -> 0 | E10: =SUMIFS('Inventory & Sales'!$D$2:$D$251,'Inventory & Sales'!$M$2:$M$251,B10) -> 0 | F10: =SUMIFS('Inventory & Sales'!$H$2:$H$251,'Inventory & Sales'!$M$2:$M$251,B10) -> 0 | G10: =SUMIFS('Inventory & Sales'!$I$2:$I$251,'Inventory & Sales'!$M$2:$M$251,B10) -> 0 | H10: ='Booth Setup'!$C$7 -> 150 | I10: ='Booth Setup'!$C$11 -> 25 | J10: =D10-E10-F10-G10-H10-I10 -> -175 | K10: =IF(C10=0,"No sales logged",IF(J10>=0,"Made money","Lost money")) -> No sales logged
B11: =DATE(YEAR(B10),MONTH(B10)+1,1) -> 46357 | C11: =COUNTIFS('Inventory & Sales'!$M$2:$M$251,B11) -> 0 | D11: =SUMIFS('Inventory & Sales'!$G$2:$G$251,'Inventory & Sales'!$M$2:$M$251,B11) -> 0 | E11: =SUMIFS('Inventory & Sales'!$D$2:$D$251,'Inventory & Sales'!$M$2:$M$251,B11) -> 0 | F11: =SUMIFS('Inventory & Sales'!$H$2:$H$251,'Inventory & Sales'!$M$2:$M$251,B11) -> 0 | G11: =SUMIFS('Inventory & Sales'!$I$2:$I$251,'Inventory & Sales'!$M$2:$M$251,B11) -> 0 | H11: ='Booth Setup'!$C$7 -> 150 | I11: ='Booth Setup'!$C$11 -> 25 | J11: =D11-E11-F11-G11-H11-I11 -> -175 | K11: =IF(C11=0,"No sales logged",IF(J11>=0,"Made money","Lost money")) -> No sales logged
B12: =DATE(YEAR(B11),MONTH(B11)+1,1) -> 46388 | C12: =COUNTIFS('Inventory & Sales'!$M$2:$M$251,B12) -> 0 | D12: =SUMIFS('Inventory & Sales'!$G$2:$G$251,'Inventory & Sales'!$M$2:$M$251,B12) -> 0 | E12: =SUMIFS('Inventory & Sales'!$D$2:$D$251,'Inventory & Sales'!$M$2:$M$251,B12) -> 0 | F12: =SUMIFS('Inventory & Sales'!$H$2:$H$251,'Inventory & Sales'!$M$2:$M$251,B12) -> 0 | G12: =SUMIFS('Inventory & Sales'!$I$2:$I$251,'Inventory & Sales'!$M$2:$M$251,B12) -> 0 | H12: ='Booth Setup'!$C$7 -> 150 | I12: ='Booth Setup'!$C$11 -> 25 | J12: =D12-E12-F12-G12-H12-I12 -> -175 | K12: =IF(C12=0,"No sales logged",IF(J12>=0,"Made money","Lost money")) -> No sales logged
B13: =DATE(YEAR(B12),MONTH(B12)+1,1) -> 46419 | C13: =COUNTIFS('Inventory & Sales'!$M$2:$M$251,B13) -> 0 | D13: =SUMIFS('Inventory & Sales'!$G$2:$G$251,'Inventory & Sales'!$M$2:$M$251,B13) -> 0 | E13: =SUMIFS('Inventory & Sales'!$D$2:$D$251,'Inventory & Sales'!$M$2:$M$251,B13) -> 0 | F13: =SUMIFS('Inventory & Sales'!$H$2:$H$251,'Inventory & Sales'!$M$2:$M$251,B13) -> 0 | G13: =SUMIFS('Inventory & Sales'!$I$2:$I$251,'Inventory & Sales'!$M$2:$M$251,B13) -> 0 | H13: ='Booth Setup'!$C$7 -> 150 | I13: ='Booth Setup'!$C$11 -> 25 | J13: =D13-E13-F13-G13-H13-I13 -> -175 | K13: =IF(C13=0,"No sales logged",IF(J13>=0,"Made money","Lost money")) -> No sales logged
B14: =DATE(YEAR(B13),MONTH(B13)+1,1) -> 46447 | C14: =COUNTIFS('Inventory & Sales'!$M$2:$M$251,B14) -> 0 | D14: =SUMIFS('Inventory & Sales'!$G$2:$G$251,'Inventory & Sales'!$M$2:$M$251,B14) -> 0 | E14: =SUMIFS('Inventory & Sales'!$D$2:$D$251,'Inventory & Sales'!$M$2:$M$251,B14) -> 0 | F14: =SUMIFS('Inventory & Sales'!$H$2:$H$251,'Inventory & Sales'!$M$2:$M$251,B14) -> 0 | G14: =SUMIFS('Inventory & Sales'!$I$2:$I$251,'Inventory & Sales'!$M$2:$M$251,B14) -> 0 | H14: ='Booth Setup'!$C$7 -> 150 | I14: ='Booth Setup'!$C$11 -> 25 | J14: =D14-E14-F14-G14-H14-I14 -> -175 | K14: =IF(C14=0,"No sales logged",IF(J14>=0,"Made money","Lost money")) -> No sales logged
B15: =DATE(YEAR(B14),MONTH(B14)+1,1) -> 46478 | C15: =COUNTIFS('Inventory & Sales'!$M$2:$M$251,B15) -> 0 | D15: =SUMIFS('Inventory & Sales'!$G$2:$G$251,'Inventory & Sales'!$M$2:$M$251,B15) -> 0 | E15: =SUMIFS('Inventory & Sales'!$D$2:$D$251,'Inventory & Sales'!$M$2:$M$251,B15) -> 0 | F15: =SUMIFS('Inventory & Sales'!$H$2:$H$251,'Inventory & Sales'!$M$2:$M$251,B15) -> 0 | G15: =SUMIFS('Inventory & Sales'!$I$2:$I$251,'Inventory & Sales'!$M$2:$M$251,B15) -> 0 | H15: ='Booth Setup'!$C$7 -> 150 | I15: ='Booth Setup'!$C$11 -> 25 | J15: =D15-E15-F15-G15-H15-I15 -> -175 | K15: =IF(C15=0,"No sales logged",IF(J15>=0,"Made money","Lost money")) -> No sales logged
B16: =DATE(YEAR(B15),MONTH(B15)+1,1) -> 46508 | C16: =COUNTIFS('Inventory & Sales'!$M$2:$M$251,B16) -> 0 | D16: =SUMIFS('Inventory & Sales'!$G$2:$G$251,'Inventory & Sales'!$M$2:$M$251,B16) -> 0 | E16: =SUMIFS('Inventory & Sales'!$D$2:$D$251,'Inventory & Sales'!$M$2:$M$251,B16) -> 0 | F16: =SUMIFS('Inventory & Sales'!$H$2:$H$251,'Inventory & Sales'!$M$2:$M$251,B16) -> 0 | G16: =SUMIFS('Inventory & Sales'!$I$2:$I$251,'Inventory & Sales'!$M$2:$M$251,B16) -> 0 | H16: ='Booth Setup'!$C$7 -> 150 | I16: ='Booth Setup'!$C$11 -> 25 | J16: =D16-E16-F16-G16-H16-I16 -> -175 | K16: =IF(C16=0,"No sales logged",IF(J16>=0,"Made money","Lost money")) -> No sales logged
B17: =DATE(YEAR(B16),MONTH(B16)+1,1) -> 46539 | C17: =COUNTIFS('Inventory & Sales'!$M$2:$M$251,B17) -> 0 | D17: =SUMIFS('Inventory & Sales'!$G$2:$G$251,'Inventory & Sales'!$M$2:$M$251,B17) -> 0 | E17: =SUMIFS('Inventory & Sales'!$D$2:$D$251,'Inventory & Sales'!$M$2:$M$251,B17) -> 0 | F17: =SUMIFS('Inventory & Sales'!$H$2:$H$251,'Inventory & Sales'!$M$2:$M$251,B17) -> 0 | G17: =SUMIFS('Inventory & Sales'!$I$2:$I$251,'Inventory & Sales'!$M$2:$M$251,B17) -> 0 | H17: ='Booth Setup'!$C$7 -> 150 | I17: ='Booth Setup'!$C$11 -> 25 | J17: =D17-E17-F17-G17-H17-I17 -> -175 | K17: =IF(C17=0,"No sales logged",IF(J17>=0,"Made money","Lost money")) -> No sales logged
B18: =DATE(YEAR(B17),MONTH(B17)+1,1) -> 46569 | C18: =COUNTIFS('Inventory & Sales'!$M$2:$M$251,B18) -> 0 | D18: =SUMIFS('Inventory & Sales'!$G$2:$G$251,'Inventory & Sales'!$M$2:$M$251,B18) -> 0 | E18: =SUMIFS('Inventory & Sales'!$D$2:$D$251,'Inventory & Sales'!$M$2:$M$251,B18) -> 0 | F18: =SUMIFS('Inventory & Sales'!$H$2:$H$251,'Inventory & Sales'!$M$2:$M$251,B18) -> 0 | G18: =SUMIFS('Inventory & Sales'!$I$2:$I$251,'Inventory & Sales'!$M$2:$M$251,B18) -> 0 | H18: ='Booth Setup'!$C$7 -> 150 | I18: ='Booth Setup'!$C$11 -> 25 | J18: =D18-E18-F18-G18-H18-I18 -> -175 | K18: =IF(C18=0,"No sales logged",IF(J18>=0,"Made money","Lost money")) -> No sales logged
B19: YEAR TOTAL | C19: =SUM(C7:C18) -> 1 | D19: =SUM(D7:D18) -> 16 | E19: =SUM(E7:E18) -> 4 | F19: =SUM(F7:F18) -> 1.6 | G19: =SUM(G7:G18) -> 0.48 | H19: =SUM(H7:H18) -> 1800 | I19: =SUM(I7:I18) -> 300 | J19: =SUM(J7:J18) -> -2090.08
B21: Months with no sales still show rent as a loss. That's on purpose: rent is due either way.
